{
  "title": "Dynamic Active Effects SRD",
  "description": "DnD 5e SRD items, features and spells configured for Dynamic Active Effects, MQoL and AT",
  "version": "6.0.01",
  "bugs": "https://github.com/kandashi/Dynamic-Effects-SRD/issues",
  "packs": [
    {
      "name": "DAE SRD Items",
      "label": "DAE SRD  Items",
      "path": "packs/equipment.db",
      "type": "Item",
      "private": false,
      "system": "dnd5e",
      "flags": {}
    },
    {
      "name": "DAE SRD Feats",
      "label": "DAE SRD Feats",
      "path": "packs/feats.db",
      "type": "Item",
      "private": false,
      "system": "dnd5e",
      "flags": {}
    },
    {
      "name": "DAE SRD Magic Items",
      "label": "SRD Magic Items",
      "path": "packs/MagicItems.db",
      "type": "Item",
      "private": false,
      "system": "dnd5e",
      "flags": {}
    }
  ],
  "url": "https://github.com/kandashi/Dynamic-Effects-SRD",
  "manifest": "https://github.com/kandashi/Dynamic-Effects-SRD/releases/latest/download/module.json",
  "download": "https://github.com/kandashi/Dynamic-Effects-SRD/releases/download/6.0.01/module.zip",
  "id": "Dynamic-Effects-SRD",
  "authors": [
    {
      "name": "Kandashi",
      "flags": {}
    }
  ],
  "relationships": {
    "requires": [
      {
        "id": "dae",
        "type": "module",
        "manifest": "https://gitlab.com/tposney/dae/raw/master/package/module.json",
        "compatibility": {}
      }
    ],
    "systems": [
      {
        "id": "dnd5e",
        "type": "system",
        "compatibility": {}
      }
    ]
  },
  "compatibility": {
    "minimum": "0.8.5",
    "verified": "0.8.6"
  }
}