{
  "title": "Drag Upload (Get Over Here!)",
  "description": "Adds the ability to drag files onto Foundry to automatically create Tokens, Tiles, Journal Pins, and Ambient Audio",
  "version": "2.2.2",
  "esmodules": [
    "dragupload.js"
  ],
  "url": "https://github.com/cswendrowski/FoundryVTT-Drag-Upload",
  "manifest": "https://github.com/cswendrowski/FoundryVTT-Drag-Upload/releases/download/latest/module.json",
  "download": "https://github.com/cswendrowski/FoundryVTT-Drag-Upload/releases/download/2.2.2/module.zip",
  "id": "dragupload",
  "authors": [
    {
      "name": "Cody Swendrowski <cody@swendrowski.us>",
      "flags": {}
    }
  ],
  "compatibility": {
    "minimum": "9",
    "verified": "10"
  }
}